sigmaepsilon/math/__init__.py
sigmaepsilon/math/approx/__init__.py
sigmaepsilon/math/approx/functions.py
sigmaepsilon/math/approx/lagrange.py
sigmaepsilon/math/approx/ls.py
sigmaepsilon/math/approx/ls_approx.py
sigmaepsilon/math/approx/ls_poly.py
sigmaepsilon/math/approx/ls_preproc.py
sigmaepsilon/math/approx/mls.py
sigmaepsilon/math/arraysetops.py
sigmaepsilon/math/decorate.py
sigmaepsilon/math/downloads.py
sigmaepsilon/math/function/__init__.py
sigmaepsilon/math/function/function.py
sigmaepsilon/math/function/functions.py
sigmaepsilon/math/function/metafunction.py
sigmaepsilon/math/function/relation.py
sigmaepsilon/math/function/symutils.py
sigmaepsilon/math/function/testfunction.py
sigmaepsilon/math/function/utils.py
sigmaepsilon/math/graph/__init__.py
sigmaepsilon/math/graph/graph.py
sigmaepsilon/math/graph/utils.py
sigmaepsilon/math/hist.py
sigmaepsilon/math/knn.py
sigmaepsilon/math/linalg/__init__.py
sigmaepsilon/math/linalg/abstract.py
sigmaepsilon/math/linalg/exceptions.py
sigmaepsilon/math/linalg/frame.py
sigmaepsilon/math/linalg/imap.py
sigmaepsilon/math/linalg/logical.py
sigmaepsilon/math/linalg/meta.py
sigmaepsilon/math/linalg/solve.py
sigmaepsilon/math/linalg/sparse/__init__.py
sigmaepsilon/math/linalg/sparse/csr.py
sigmaepsilon/math/linalg/sparse/jaggedarray.py
sigmaepsilon/math/linalg/sparse/utils.py
sigmaepsilon/math/linalg/tensor.py
sigmaepsilon/math/linalg/testing.py
sigmaepsilon/math/linalg/tr.py
sigmaepsilon/math/linalg/utils.py
sigmaepsilon/math/linalg/vector.py
sigmaepsilon/math/logical.py
sigmaepsilon/math/mathtypes.py
sigmaepsilon/math/metautils.py
sigmaepsilon/math/numint.py
sigmaepsilon/math/optimize/__init__.py
sigmaepsilon/math/optimize/bga.py
sigmaepsilon/math/optimize/ga.py
sigmaepsilon/math/optimize/lp.py
sigmaepsilon/math/optimize/state.py
sigmaepsilon/math/utils.py
sigmaepsilon_math-2.3.0.dist-info/METADATA
sigmaepsilon_math-2.3.0.dist-info/WHEEL
sigmaepsilon_math-2.3.0.dist-info/licenses/LICENSE
sigmaepsilon_math-2.3.0.dist-info/RECORD
