Metadata-Version: 2.4
Name: sigmaepsilon.math
Version: 2.3.0
Summary: A Python Library for Applied Mathematics in Physical Sciences.
License: MIT
License-File: LICENSE
Keywords: engineering,mathematics,optimization,vector,tensor,vector algebra,tensor algebra,symbolic mathematics,nonlinear optimization
Author: Bence Balogh
Author-email: bencebalogh@sigmaepsilon.com
Maintainer: Bence Balogh
Maintainer-email: bencebalogh@sigmaepsilon.com
Requires-Python: >=3.10,<4.0
Classifier: Development Status :: 5 - Production/Stable
Classifier: License :: OSI Approved :: MIT License
Classifier: Operating System :: OS Independent
Classifier: Programming Language :: Python :: 3
Classifier: Programming Language :: Python :: 3.10
Classifier: Programming Language :: Python :: 3.11
Classifier: Programming Language :: Python :: 3.12
Classifier: Programming Language :: Python :: 3.13
Classifier: Programming Language :: Python :: 3.14
Classifier: Programming Language :: Python :: 3 :: Only
Requires-Dist: awkward (>2.0.8)
Requires-Dist: numba (>=0.56.4)
Requires-Dist: numpy (>=1.26.4,<2.0.0)
Requires-Dist: pydantic (>=2.0.2)
Requires-Dist: scipy (>=1.12.0,<2.0.0)
Requires-Dist: sigmaepsilon-core (>=1.2.2,<2.0.0)
Requires-Dist: sigmaepsilon-deepdict (>=3.0.1,<4.0.0)
Requires-Dist: sympy (>=1.11.1)
Requires-Dist: zipp (>=3.19.1)
Project-URL: Documentation, https://sigmaepsilonmath.readthedocs.io/en/latest/?badge=latest
Project-URL: Homepage, https://github.com/sigma-epsilon/sigmaepsilon.math
Project-URL: Repository, https://github.com/sigma-epsilon/sigmaepsilon.math
